grai/__init__.py
grai/cli/__init__.py
grai/cli/main.py
grai/core/__init__.py
grai/core/models.py
grai/core/cache/__init__.py
grai/core/cache/build_cache.py
grai/core/compiler/__init__.py
grai/core/compiler/cypher_compiler.py
grai/core/exporter/__init__.py
grai/core/exporter/ir_exporter.py
grai/core/lineage/__init__.py
grai/core/lineage/lineage_tracker.py
grai/core/loader/__init__.py
grai/core/loader/neo4j_loader.py
grai/core/parser/__init__.py
grai/core/parser/yaml_parser.py
grai/core/validator/__init__.py
grai/core/validator/validator.py
grai/core/visualizer/__init__.py
grai/core/visualizer/visualizer.py
grai/templates/__init__.py
grai_build-0.3.2.dist-info/licenses/LICENSE
grai_build-0.3.2.dist-info/METADATA
grai_build-0.3.2.dist-info/WHEEL
grai_build-0.3.2.dist-info/entry_points.txt
grai_build-0.3.2.dist-info/top_level.txt
grai_build-0.3.2.dist-info/RECORD
